<?xml version='1.0' encoding='UTF-8'?>
<NineML xmlns="http://nineml.org/9ML/0.3">
  <ComponentClass name="Poisson">
    <EventPort mode="send" name="spikeOutput"/>
    <Parameter dimension="" name="rate"/>
    <Dynamics>
      <Regime name="default">
        <OnCondition target_regime="default">
          <StateAssignment variable="t_next">
            <MathInline>t + random.exponential(1000/rate)</MathInline>
          </StateAssignment>
          <EventOut port="spikeOutput"/>
          <Trigger>
            <MathInline>t &gt; t_next</MathInline>
          </Trigger>
        </OnCondition>
      </Regime>
      <StateVariable dimension="time" name="t_next"/>
    </Dynamics>
  </ComponentClass>
</NineML>
